upgradelink_api_python/__init__.py
upgradelink_api_python/client.py
upgradelink_api_python/models.py
upgradelink_api_python-3.0.1.dist-info/METADATA
upgradelink_api_python-3.0.1.dist-info/WHEEL
upgradelink_api_python-3.0.1.dist-info/RECORD
