Metadata-Version: 2.3
Name: upgradelink-api-python
Version: 3.0.1
Summary: upgradelink-api-python
Author: toolsetlink
Author-email: toolsetlink@163.com
Requires-Python: >=3.6
Classifier: Programming Language :: Python :: 3
Classifier: Programming Language :: Python :: 3.6
Classifier: Programming Language :: Python :: 3.7
Classifier: Programming Language :: Python :: 3.8
Classifier: Programming Language :: Python :: 3.9
Classifier: Programming Language :: Python :: 3.10
Classifier: Programming Language :: Python :: 3.11
Classifier: Programming Language :: Python :: 3.12
Classifier: Programming Language :: Python :: 3.13
Requires-Dist: alibabacloud-tea (>=0.2.0)
Requires-Dist: alibabacloud-tea-util (>=0.3.0)
Requires-Dist: darabonba-base-python (>=0.0.1)
